memcnn/__init__.py
memcnn/train.py
memcnn/config/__init__.py
memcnn/config/config.json.example
memcnn/config/experiments.json
memcnn/config/tests/__init__.py
memcnn/config/tests/test_config.py
memcnn/data/__init__.py
memcnn/data/cifar.py
memcnn/data/sampling.py
memcnn/data/tests/__init__.py
memcnn/data/tests/test_cifar.py
memcnn/data/tests/test_sampling.py
memcnn/experiment/__init__.py
memcnn/experiment/factory.py
memcnn/experiment/manager.py
memcnn/experiment/tests/__init__.py
memcnn/experiment/tests/test_factory.py
memcnn/experiment/tests/test_manager.py
memcnn/models/__init__.py
memcnn/models/additive.py
memcnn/models/affine.py
memcnn/models/resnet.py
memcnn/models/revop.py
memcnn/models/tests/__init__.py
memcnn/models/tests/test_amp.py
memcnn/models/tests/test_couplings.py
memcnn/models/tests/test_is_invertible_module.py
memcnn/models/tests/test_memory_saving.py
memcnn/models/tests/test_models.py
memcnn/models/tests/test_multi.py
memcnn/models/tests/test_resnet.py
memcnn/models/tests/test_revop.py
memcnn/models/tests/test_split_dim.py
memcnn/trainers/__init__.py
memcnn/trainers/classification.py
memcnn/trainers/tests/__init__.py
memcnn/trainers/tests/test_classification.py
memcnn/trainers/tests/test_train.py
memcnn/utils/__init__.py
memcnn/utils/log.py
memcnn/utils/loss.py
memcnn/utils/stats.py
memcnn/utils/tests/__init__.py
memcnn/utils/tests/test_log.py
memcnn/utils/tests/test_loss.py
memcnn/utils/tests/test_stats.py
memcnn-1.5.2.dist-info/AUTHORS.rst
memcnn-1.5.2.dist-info/LICENSE.txt
memcnn-1.5.2.dist-info/METADATA
memcnn-1.5.2.dist-info/WHEEL
memcnn-1.5.2.dist-info/top_level.txt
memcnn-1.5.2.dist-info/RECORD
