Metadata-Version: 2.1
Name: memcnn
Version: 1.5.2
Summary: A PyTorch framework for developing memory efficient deep invertible networks.
Home-page: http://pypi.python.org/pypi/memcnn/
Author: S.C. van de Leemput
Author-email: silvandeleemput@gmail.com
License: LICENSE.txt
Keywords: memcnn invertible PyTorch
Platform: UNKNOWN
Classifier: License :: OSI Approved :: MIT License
Classifier: Programming Language :: Python :: 3
Classifier: Programming Language :: Python :: 3.6
Classifier: Programming Language :: Python :: 3.7
Classifier: Development Status :: 3 - Alpha
Classifier: Intended Audience :: Science/Research
Classifier: Topic :: Scientific/Engineering
Classifier: Topic :: Scientific/Engineering :: Medical Science Apps.
Classifier: Topic :: Scientific/Engineering :: Information Analysis
Classifier: Topic :: Software Development :: Libraries
Classifier: Operating System :: OS Independent
Requires-Dist: numpy
Requires-Dist: SimpleITK
Requires-Dist: torch (>=1.0.0)
Requires-Dist: torchvision
Requires-Dist: tqdm
Requires-Dist: pathlib2
